{
  "nodes": [
    {
      "id": "editorial-plate-04-receipt",
      "label": "Editorial Plate 04: Receipt",
      "file_type": "image",
      "source_file": "apps/web/public/brand/editorial-plate-04-receipt.jpg"
    },
    {
      "id": "data-receipt-section",
      "label": "Data Receipt Landing Section (Section 4)",
      "file_type": "concept",
      "source_file": "apps/web/public/brand/editorial-plate-04-receipt.jpg"
    },
    {
      "id": "paper-receipt-motif",
      "label": "Paper Receipt Visual Motif",
      "file_type": "design_element",
      "source_file": "apps/web/public/brand/editorial-plate-04-receipt.jpg"
    },
    {
      "id": "warm-golden-light",
      "label": "Warm Golden-Hour Lighting",
      "file_type": "design_element",
      "source_file": "apps/web/public/brand/editorial-plate-04-receipt.jpg"
    },
    {
      "id": "human-hand-interaction",
      "label": "Human Hand Holding Receipt",
      "file_type": "design_element",
      "source_file": "apps/web/public/brand/editorial-plate-04-receipt.jpg"
    },
    {
      "id": "wooden-table-surface",
      "label": "Wooden Table Surface",
      "file_type": "design_element",
      "source_file": "apps/web/public/brand/editorial-plate-04-receipt.jpg"
    },
    {
      "id": "spotify-wrapped-analogy",
      "label": "Spotify Wrapped-Style Shareable Card",
      "file_type": "concept",
      "source_file": "apps/web/public/brand/editorial-plate-04-receipt.jpg"
    },
    {
      "id": "time-xray-feature",
      "label": "Time X-Ray Feature",
      "file_type": "concept",
      "source_file": "apps/web/public/brand/editorial-plate-04-receipt.jpg"
    },
    {
      "id": "editorial-photography-style",
      "label": "Editorial Photography Style",
      "file_type": "design_element",
      "source_file": "apps/web/public/brand/editorial-plate-04-receipt.jpg"
    },
    {
      "id": "meldar-brand",
      "label": "Meldar Brand Identity",
      "file_type": "concept",
      "source_file": "apps/web/public/brand/editorial-plate-04-receipt.jpg"
    },
    {
      "id": "tangible-data-metaphor",
      "label": "Tangible Data Metaphor (Physical Receipt = Digital Data)",
      "file_type": "concept",
      "source_file": "apps/web/public/brand/editorial-plate-04-receipt.jpg"
    },
    {
      "id": "warm-cream-surface-palette",
      "label": "Warm Cream / Natural Palette (#faf9f6)",
      "file_type": "design_element",
      "source_file": "apps/web/public/brand/editorial-plate-04-receipt.jpg"
    }
  ],
  "edges": [
    {
      "source": "editorial-plate-04-receipt",
      "target": "data-receipt-section",
      "relation": "ILLUSTRATES",
      "confidence": "EXTRACTED",
      "confidence_score": 1.0,
      "source_file": "apps/web/public/brand/editorial-plate-04-receipt.jpg",
      "weight": 1.0
    },
    {
      "source": "editorial-plate-04-receipt",
      "target": "paper-receipt-motif",
      "relation": "DEPICTS",
      "confidence": "EXTRACTED",
      "confidence_score": 1.0,
      "source_file": "apps/web/public/brand/editorial-plate-04-receipt.jpg",
      "weight": 1.0
    },
    {
      "source": "editorial-plate-04-receipt",
      "target": "warm-golden-light",
      "relation": "USES_LIGHTING",
      "confidence": "EXTRACTED",
      "confidence_score": 1.0,
      "source_file": "apps/web/public/brand/editorial-plate-04-receipt.jpg",
      "weight": 1.0
    },
    {
      "source": "editorial-plate-04-receipt",
      "target": "human-hand-interaction",
      "relation": "DEPICTS",
      "confidence": "EXTRACTED",
      "confidence_score": 1.0,
      "source_file": "apps/web/public/brand/editorial-plate-04-receipt.jpg",
      "weight": 1.0
    },
    {
      "source": "editorial-plate-04-receipt",
      "target": "wooden-table-surface",
      "relation": "DEPICTS",
      "confidence": "EXTRACTED",
      "confidence_score": 1.0,
      "source_file": "apps/web/public/brand/editorial-plate-04-receipt.jpg",
      "weight": 1.0
    },
    {
      "source": "editorial-plate-04-receipt",
      "target": "editorial-photography-style",
      "relation": "EXEMPLIFIES",
      "confidence": "EXTRACTED",
      "confidence_score": 1.0,
      "source_file": "apps/web/public/brand/editorial-plate-04-receipt.jpg",
      "weight": 1.0
    },
    {
      "source": "editorial-plate-04-receipt",
      "target": "meldar-brand",
      "relation": "BELONGS_TO",
      "confidence": "EXTRACTED",
      "confidence_score": 1.0,
      "source_file": "apps/web/public/brand/editorial-plate-04-receipt.jpg",
      "weight": 1.0
    },
    {
      "source": "data-receipt-section",
      "target": "spotify-wrapped-analogy",
      "relation": "MODELED_AFTER",
      "confidence": "INFERRED",
      "confidence_score": 0.9,
      "source_file": "apps/web/public/brand/editorial-plate-04-receipt.jpg",
      "weight": 0.9
    },
    {
      "source": "data-receipt-section",
      "target": "time-xray-feature",
      "relation": "VISUALIZES_OUTPUT_OF",
      "confidence": "INFERRED",
      "confidence_score": 0.85,
      "source_file": "apps/web/public/brand/editorial-plate-04-receipt.jpg",
      "weight": 0.85
    },
    {
      "source": "paper-receipt-motif",
      "target": "tangible-data-metaphor",
      "relation": "EMBODIES",
      "confidence": "INFERRED",
      "confidence_score": 0.9,
      "source_file": "apps/web/public/brand/editorial-plate-04-receipt.jpg",
      "weight": 0.9
    },
    {
      "source": "tangible-data-metaphor",
      "target": "data-receipt-section",
      "relation": "CONCEPTUAL_BASIS_FOR",
      "confidence": "INFERRED",
      "confidence_score": 0.85,
      "source_file": "apps/web/public/brand/editorial-plate-04-receipt.jpg",
      "weight": 0.85
    },
    {
      "source": "human-hand-interaction",
      "target": "tangible-data-metaphor",
      "relation": "REINFORCES",
      "confidence": "INFERRED",
      "confidence_score": 0.8,
      "source_file": "apps/web/public/brand/editorial-plate-04-receipt.jpg",
      "weight": 0.8
    },
    {
      "source": "warm-golden-light",
      "target": "warm-cream-surface-palette",
      "relation": "ALIGNS_WITH",
      "confidence": "INFERRED",
      "confidence_score": 0.85,
      "source_file": "apps/web/public/brand/editorial-plate-04-receipt.jpg",
      "weight": 0.85
    },
    {
      "source": "wooden-table-surface",
      "target": "warm-cream-surface-palette",
      "relation": "ECHOES",
      "confidence": "INFERRED",
      "confidence_score": 0.8,
      "source_file": "apps/web/public/brand/editorial-plate-04-receipt.jpg",
      "weight": 0.8
    },
    {
      "source": "warm-cream-surface-palette",
      "target": "meldar-brand",
      "relation": "PART_OF_BRAND_PALETTE",
      "confidence": "INFERRED",
      "confidence_score": 0.85,
      "source_file": "apps/web/public/brand/editorial-plate-04-receipt.jpg",
      "weight": 0.85
    },
    {
      "source": "editorial-photography-style",
      "target": "meldar-brand",
      "relation": "DEFINES_VISUAL_LANGUAGE_OF",
      "confidence": "INFERRED",
      "confidence_score": 0.9,
      "source_file": "apps/web/public/brand/editorial-plate-04-receipt.jpg",
      "weight": 0.9
    },
    {
      "source": "editorial-plate-04-receipt",
      "target": "warm-cream-surface-palette",
      "relation": "USES_COLOR_PALETTE",
      "confidence": "INFERRED",
      "confidence_score": 0.8,
      "source_file": "apps/web/public/brand/editorial-plate-04-receipt.jpg",
      "weight": 0.8
    },
    {
      "source": "tangible-data-metaphor",
      "target": "meldar-brand",
      "relation": "SUPPORTS_POSITIONING",
      "confidence": "INFERRED",
      "confidence_score": 0.8,
      "source_file": "apps/web/public/brand/editorial-plate-04-receipt.jpg",
      "weight": 0.8
    }
  ],
  "hyperedges": [
    {
      "nodes": ["paper-receipt-motif", "human-hand-interaction", "warm-golden-light", "wooden-table-surface"],
      "relation": "COMPOSE_EDITORIAL_SCENE",
      "confidence": "EXTRACTED",
      "confidence_score": 1.0,
      "source_file": "apps/web/public/brand/editorial-plate-04-receipt.jpg",
      "weight": 1.0
    },
    {
      "nodes": ["tangible-data-metaphor", "spotify-wrapped-analogy", "data-receipt-section"],
      "relation": "CONCEPTUAL_TRIAD_DATA_RECEIPT",
      "confidence": "INFERRED",
      "confidence_score": 0.85,
      "source_file": "apps/web/public/brand/editorial-plate-04-receipt.jpg",
      "weight": 0.85
    }
  ],
  "input_tokens": 0,
  "output_tokens": 0
}
